[
  {
    "class_name": "Piano",
    "image": "piano.jpg",
    "instructor_name": "John Smith",
    "instructor_email": "john@example.com",
    "price": 50,
    "available_seat": 10,
    "status": "approved",
    "enrolled": 0
  },
  {
    "class_name": "Guitar",
    "image": "guitar.jpg",
    "instructor_name": "Jane Doe",
    "instructor_email": "jane@example.com",
    "price": 40,
    "available_seat": 8,
    "status": "approved",
    "enrolled": 0
  },
  {
    "class_name": "Violin",
    "image": "violin.jpg",
    "instructor_name": "David Johnson",
    "instructor_email": "david@example.com",
    "price": 55,
    "available_seat": 5,
    "status": "pending",
    "enrolled": 0
  },
  {
    "class_name": "Drums",
    "image": "drums.jpg",
    "instructor_name": "Sarah Davis",
    "instructor_email": "sarah@example.com",
    "price": 45,
    "available_seat": 12,
    "status": "approved",
    "enrolled": 0
  },
  {
    "class_name": "Saxophone",
    "image": "saxophone.jpg",
    "instructor_name": "Michael Wilson",
    "instructor_email": "michael@example.com",
    "price": 60,
    "available_seat": 6,
    "status": "denied",
    "enrolled": 0
  },
  {
    "class_name": "Flute",
    "image": "flute.jpg",
    "instructor_name": "Emily Anderson",
    "instructor_email": "emily@example.com",
    "price": 35,
    "available_seat": 7,
    "status": "approved",
    "enrolled": 0
  }
]
